<?xml version="1.0" encoding="UTF-8" standalone="yes"?>
<people>
    <person>
        <firstname>Ned</firstname>
        <lastname>Stark</lastname>
        <birthdate>1973-06-28T15:19:44.000+2:00</birthdate>
        <healthprofile>
            <lastupdate>2014-05-08T21:16:51.000+2:00</lastupdate>
            <weight>80.0</weight>
            <height>1.88</height>
            <bmi>24.9</bmi>
        </healthprofile>
    </person>
    <person>
        <firstname>Cersi</firstname>
        <lastname>Lannister</lastname>
        <birthdate>1976-06-25T15:30:14.000+2:00</birthdate>
        <healthprofile>
            <lastupdate>2015-09-09T01:51:53.000+2:00</lastupdate>
            <weight>72.0</weight>
            <height>1.78</height>
            <bmi>23.1</bmi>
        </healthprofile>
    </person>
    <person>
        <firstname>Jon</firstname>
        <lastname>Snow</lastname>
        <birthdate>1973-01-04T01:33:45.000+2:00</birthdate>
        <healthprofile>
            <lastupdate>2014-10-18T17:53:31.000+2:00</lastupdate>
            <weight>88.0</weight>
            <height>1.89</height>
            <bmi>22.0</bmi>
        </healthprofile>
    </person>
    <person>
        <firstname>Danarys</firstname>
        <lastname>Targeryan</lastname>
        <birthdate>1989-06-23T05:25:35.000+2:00</birthdate>
        <healthprofile>
            <lastupdate>2015-10-06T15:16:34.000+2:00</lastupdate>
            <weight>75.0</weight>
            <height>1.81</height>
            <bmi>21.6</bmi>
        </healthprofile>
    </person>
    <person>
        <firstname>Margery</firstname>
        <lastname>Tyrell</lastname>
        <birthdate>1977-02-02T17:32:38.000+2:00</birthdate>
        <healthprofile>
            <lastupdate>2015-05-14T21:00:17.000+2:00</lastupdate>
            <weight>83.0</weight>
            <height>1.86</height>
            <bmi>20.9</bmi>
        </healthprofile>
    </person>
</people>
